mindsight_auth_api/__init__.py
mindsight_auth_api/helpers/__init__.py
mindsight_auth_api/helpers/base_requests.py
mindsight_auth_api/helpers/exceptions.py
mindsight_auth_api/helpers/models.py
mindsight_auth_api/settings.py
mindsight_auth_api/src/__init__.py
mindsight_auth_api/src/auth.py
mindsight_auth_api/utils/__init__.py
mindsight_auth_api/utils/aux_functions.py
mindsight_auth_api-0.0.2.dist-info/LICENSE
mindsight_auth_api-0.0.2.dist-info/METADATA
mindsight_auth_api-0.0.2.dist-info/WHEEL
mindsight_auth_api-0.0.2.dist-info/RECORD
